langscikw/__init__.py
langscikw/cli.py
langscikw/kwe_toolkit.py
langscikw/langscikw.py
langscikw/tfidfmodel.py
langscikw/yakemodel.py
langscikw/corpora/keywordslist.txt
langscikw/corpora/stopwords.txt
langscikw/yakefork/Levenshtein.py
langscikw/yakefork/__init__.py
langscikw/yakefork/datarepresentation.py
langscikw/yakefork/yake.py
langscikw-0.0.1.dist-info/LICENSE
langscikw-0.0.1.dist-info/METADATA
langscikw-0.0.1.dist-info/WHEEL
langscikw-0.0.1.dist-info/entry_points.txt
langscikw-0.0.1.dist-info/top_level.txt
langscikw-0.0.1.dist-info/RECORD
