Metadata-Version: 2.1
Name: langscikw
Version: 0.0.1
Summary: Keyword extraction from linguistic publications
Home-page: https://pypi.python.org/pypi/langscikw
Author: Noel Simmel
Author-email: noelsimmel@protonmail.com
License: LGPLv3
Project-URL: Source, https://github.com/langsci/langscikw
Project-URL: Bug Reports, https://github.com/langsci/langscikw/issues
Project-URL: Language Science Press, https://langsci-press.org/
Keywords: langsci keywordextraction indexing keywords naturallanguageprocessing nlp
Platform: UNKNOWN
Classifier: License :: OSI Approved :: GNU General Public License v3 (GPLv3)
Classifier: Intended Audience :: Developers
Classifier: Intended Audience :: Science/Research
Classifier: Intended Audience :: End Users/Desktop
Classifier: Topic :: Scientific/Engineering :: Information Analysis
Classifier: Topic :: Software Development :: Libraries :: Python Modules
Classifier: Topic :: Text Processing :: Indexing
Classifier: Topic :: Text Processing :: Linguistic
Classifier: Natural Language :: English
Classifier: License :: OSI Approved :: MIT License
Classifier: Operating System :: OS Independent
Classifier: Programming Language :: Python :: 3
Classifier: Programming Language :: Python :: 3.7
Classifier: Programming Language :: Python :: 3.8
Classifier: Programming Language :: Python :: 3.9
Classifier: Programming Language :: Python :: 3 :: Only
Requires-Python: >=3.7, <4
License-File: LICENSE
Requires-Dist: scikit-learn (==0.24.2)
Requires-Dist: regex (==2021.4.4)
Requires-Dist: jellyfish
Requires-Dist: joblib
Requires-Dist: networkx (==2.5.1)
Requires-Dist: segtok
